[{"yt":"KejMIQu0hE0","title":"Core e Addome: Esercizi Per Addominali A Casa Per Principianti","dur":"9:00","kcal":40,"lvl":"principiante","fid":2691},{"yt":"WFrgVWY7WBM","title":"Esercizi Per Principianti Senza Salti: Cardio e Addominali","dur":"13:00","kcal":61,"lvl":"principiante","fid":2678},{"yt":"4MKM-UOhTCw","title":"Core e Addominali: Allenamento Veloce Per Tonificare L'Addome","dur":"14:00","kcal":67,"lvl":"avanzato","fid":2657},{"yt":"guCGslMzv3Y","title":"Esercizi Per L'Addome: Esercizi Addominali Per Principianti","dur":"13:00","kcal":39,"lvl":"principiante","fid":2651},{"yt":"kL1ZhbsumZo","title":"Allenamento Veloce Con Esercizi Per Principianti: Addominali E Core","dur":"9:00","kcal":26,"lvl":"principiante","fid":2650},{"yt":"BP8lDfv3hLc","title":"Core Workout 16 Minuti: Allenamento Veloce con Addominali e Plank","dur":"16:00","kcal":63,"lvl":"intermedio","fid":2379},{"yt":"joaXiWdBoo4","title":"13 Minuti: Allenamento Veloce con Addominali e Plank Per Principianti","dur":"13:00","kcal":54,"lvl":"principiante","fid":2378},{"yt":"JvgTWsFH6fk","title":"Esercizi Per Addominali A Casa: Workout Addome e Core Per Principianti","dur":"9:00","kcal":40,"lvl":"principiante","fid":1763},{"yt":"6seE9hKtWJM","title":"Addome Tonico: Esercizi Per Addominali e Core Stability","dur":"14:00","kcal":42,"lvl":"intermedio","fid":1732},{"yt":"rNKfy2_KcWA","title":"Core Stability: Allenamento Addominali e Rinforzo del Core","dur":"14:00","kcal":54,"lvl":"intermedio","fid":1720},{"yt":"s5GkfjQhpBc","title":"Tonificare L'Addome: Esercizi Addominali Per Principianti","dur":"9:00","kcal":33,"lvl":"principiante","fid":1718},{"yt":"bo0yiam-c_w","title":"Addominali Tonici: Circuito Con Esercizi  Per Addominali e Core","dur":"17:00","kcal":79,"lvl":"avanzato","fid":1684},{"yt":"4Jst4-z_mos","title":"Cardio & Core: 13 Minuti Con Cardio Ed Esercizi Per La Core Stability","dur":"13:00","kcal":77,"lvl":"principiante","fid":1532},{"yt":"DHN95fOQpZM","title":"Addominali: Esercizi Per Principianti Con Cardio","dur":"10:00","kcal":62,"lvl":"principiante","fid":1531},{"yt":"0grWXIA8HT0","title":"22 Minuti Con Esercizi Avanzati Per Gli Addominali E Core Stability","dur":"22:00","kcal":71,"lvl":"avanzato","fid":1426},{"yt":"sSOuLDv3pLc","title":"Esercizi Addominali: Allenamento Veloce Plank & Crunch","dur":"16:00","kcal":61,"lvl":"intermedio","fid":1419},{"yt":"gX8ko8R6jp4","title":"Addome Tonico Con Esercizi Addominali E Core Stability - 10 Minuti","dur":"10:00","kcal":32,"lvl":"avanzato","fid":1417},{"yt":"b2A6yqsN5uY","title":"Tonificazione Addome: Esercizi Addominali E Core Stability - 10 Minuti","dur":"10:00","kcal":31,"lvl":"intermedio","fid":1416},{"yt":"YqcC5Jp2n1o","title":"Addominali E Core Stability: 10 Minuti Per Un Addome Tonico e Forte","dur":"10:00","kcal":34,"lvl":"intermedio","fid":1415},{"yt":"qaXSqYjbwT0","title":"Addome Tonico 8 Minuti: Esercizi A Casa Per Addominali","dur":"8:00","kcal":27,"lvl":"intermedio","fid":1411},{"yt":"rkiPsMhFWWQ","title":"Addominali e Core Stability: Esercizi Per Migliorare Controllo e Stabilità","dur":"13:00","kcal":35,"lvl":"intermedio","fid":1376},{"yt":"QmjZgCB5Q40","title":"Core e Addominali: 8 Minuti Con Esercizi Per Tonificare L'Addome","dur":"8:00","kcal":36,"lvl":"intermedio","fid":1368},{"yt":"Ixyr2er21Wo","title":"Esercizi Per Gli Addominali A Casa Per Principianti","dur":"9:00","kcal":30,"lvl":"principiante","fid":1322},{"yt":"4XFL-ZgkIUk","title":"Esercizi Addominali: Allenamento Veloce Con Esercizi Per Addome e Core Stability","dur":"12:00","kcal":69,"lvl":"avanzato","fid":1257},{"yt":"W2Xma8rfYxw","title":"Allenamento Addominali: 11 Minuti Con Esercizi Per Addominali e Core Sability","dur":"11:00","kcal":75,"lvl":"intermedio","fid":1132},{"yt":"gJGqdW9TaGk","title":"Esercizi Per Addominali Forti e Tonici: Allenamento Per Principianti Plus","dur":"13:00","kcal":44,"lvl":"principiante","fid":1126},{"yt":"KW4h-hfz-4w","title":"Esercizi Addominali A Casa: Allenamento Per Principianti","dur":"9:00","kcal":41,"lvl":"principiante","fid":1101},{"yt":"oRvxeVEGPbc","title":"Super Core V3! Allenamento Avanzato Addominali e Core Stability","dur":"20:00","kcal":181,"lvl":"avanzato","fid":1078},{"yt":"NKHT72mm21w","title":"Esercizi Addominali: Allenamento Completo Per Addominali (Avanzato)","dur":"15:00","kcal":98,"lvl":"avanzato","fid":1075},{"yt":"vM8l2AIXew4","title":"Addominali: Esercizi Per Addominali A Casa (In Piedi e A Terra)","dur":"18:00","kcal":95,"lvl":"intermedio","fid":860},{"yt":"W9-dLDM18pY","title":"Esercizi Addominali, Plank & Core per Tonificare Pancia e Fianchi","dur":"12:00","kcal":60,"lvl":"intermedio","fid":777},{"yt":"9Q-QgK5YhuY","title":"Plank e Addominali! Esercizi A Casa Per Addominali e Core Stability","dur":"11:00","kcal":40,"lvl":"principiante","fid":776},{"yt":"JZgT2ZFdKxY","title":"Allenamento Veloce Addominali - 4 minuti di Esercizi Per L'addome","dur":"4:00","kcal":29,"lvl":"principiante","fid":684},{"yt":"workF6cNM0w","title":"Plank e Addominali! Esercizi Per Addominali Tonici E Core Stability","dur":"10:00","kcal":62,"lvl":"intermedio","fid":535},{"yt":"OpiHrzF352s","title":"Addominali Tonici! Esercizi Addominali A Terra e In Piedi!","dur":"10:00","kcal":66,"lvl":"principiante","fid":534},{"yt":"L78C64eWKsg","title":"Addominali Tonici! Allenamento Completo Per Addominali E Core Stability","dur":"18:00","kcal":72,"lvl":"avanzato","fid":397},{"yt":"-scf2sMa9gI","title":"Esercizi Addominali A Casa: Allenamento Completo Per Addominali Tonici","dur":"15:00","kcal":88,"lvl":"avanzato","fid":396},{"yt":"esfjf6UedAk","title":"Esercizi Per Addominali Con Cardio Ad Alta Intensità","dur":"10:00","kcal":73,"lvl":"avanzato","fid":317},{"yt":"bLbxjN00AMg","title":"Esercizi Per Addominali E Core Stability (con palla)","dur":"23:00","kcal":63,"lvl":"avanzato","fid":239},{"yt":"VsH46j_lIOI","title":"Esercizi Addominali: Circuito Con Esercizi Per Tonificare L’Addome","dur":"27:00","kcal":54,"lvl":"avanzato","fid":198},{"yt":"USqZlLm3M1g","title":"15 Minuti Di Esercizi Per Tonificare Gli Addominali","dur":"15:00","kcal":44,"lvl":"intermedio","fid":166},{"yt":"rQeWcks6DKU","title":"Pancia Piatta 1: 13 Minuti di Esercizi per gli Addominali","dur":"13:00","kcal":26,"lvl":"principiante","fid":165},{"yt":"QzrsBajkU00","title":"Core Stability: Esercizi Per Dimagrire Fianchi e Girovita","dur":"10:00","kcal":36,"lvl":"intermedio","fid":103},{"yt":"F3aaZz0aPS8","title":"Esercizi Addominali e Core Stability: Allenamento Breve e Intenso","dur":"11:00","kcal":65,"lvl":"avanzato","fid":92},{"yt":"7sKGs7KvtP8","title":"Addominali Scolpiti! 11 Minuti Con Esercizi Intensi Per Tonificare Gli Addominali","dur":"11:00","kcal":47,"lvl":"avanzato","fid":89},{"yt":"czSx3hoPqB8","title":"Core Stability Allenamento Funzionale Completo","dur":"25:00","kcal":145,"lvl":"intermedio","fid":45},{"yt":"uEzbarctOY0","title":"Pancia Piatta 2: Tonificazione Addominali (Liv. Intermedio)","dur":"12:00","kcal":56,"lvl":"intermedio","fid":44}]